mitWppSdk/WppClient.py
mitWppSdk/WppException.py
mitWppSdk/__init__.py
mitWppSdk/builders.py
mitWppSdk/validators.py
mitWppSdk/util/AESHelper.py
mitWppSdk/util/WppHttpHelper.py
mitWppSdk/util/__init__.py
mitWppSdk-0.0.3.dist-info/LICENSE
mitWppSdk-0.0.3.dist-info/METADATA
mitWppSdk-0.0.3.dist-info/WHEEL
mitWppSdk-0.0.3.dist-info/top_level.txt
mitWppSdk-0.0.3.dist-info/RECORD
