Metadata-Version: 2.1
Name: mitWppSdk
Version: 0.0.3
Summary: SDK de integracion para generador de ligas
Author-email: Mercadotecnia Ideas y Tecnologia <developers@mitec.com.mx>
Project-URL: Homepage, https://github.com/opardor/mit-wpp-python-sdk
Project-URL: Bug Tracker, https://github.com/opardor/mit-wpp-python-sdk/issues
Classifier: Programming Language :: Python :: 3
Classifier: License :: OSI Approved :: MIT License
Classifier: Operating System :: OS Independent
Requires-Python: >=3.9
License-File: LICENSE
